dotpkg/__init__.py
dotpkg/__main__.py
dotpkg/commands.py
dotpkg/constants.py
dotpkg/install.py
dotpkg/manifest.py
dotpkg/options.py
dotpkg/resolve.py
dotpkg/utils/__init__.py
dotpkg/utils/file.py
dotpkg/utils/log.py
dotpkg/utils/prompt.py
dotpkg-0.0.1.dist-info/LICENSE
dotpkg-0.0.1.dist-info/METADATA
dotpkg-0.0.1.dist-info/WHEEL
dotpkg-0.0.1.dist-info/entry_points.txt
dotpkg-0.0.1.dist-info/top_level.txt
dotpkg-0.0.1.dist-info/RECORD
