Metadata-Version: 2.1
Name: dotpkg
Version: 0.0.1
Summary: Package manager for your dotfiles
License: MIT License
Keywords: package-manager,dotfiles
Classifier: Topic :: Utilities
Requires-Python: >=3.9
License-File: LICENSE
